app/__init__.py
app/msstitch.py
app/actions/__init__.py
app/actions/merge.py
app/actions/proteins.py
app/actions/psmtopeptable.py
app/actions/sequence.py
app/actions/lookups/__init__.py
app/actions/lookups/quant.py
app/actions/lookups/sequence.py
app/actions/lookups/spectra.py
app/actions/percolator/__init__.py
app/actions/percolator/filters.py
app/actions/percolator/split.py
app/actions/psmtable/__init__.py
app/actions/psmtable/filtering.py
app/actions/psmtable/isosummarize.py
app/actions/psmtable/percolator.py
app/actions/psmtable/refine.py
app/actions/psmtable/splitmerge.py
app/dataformats/__init__.py
app/dataformats/peptable.py
app/dataformats/prottable.py
app/dataformats/psms.py
app/dataformats/qvality.py
app/drivers/__init__.py
app/drivers/base.py
app/drivers/lookups.py
app/drivers/merge.py
app/drivers/options.py
app/drivers/peptable.py
app/drivers/percolator.py
app/drivers/prottable.py
app/drivers/psmtable.py
app/drivers/sequence.py
app/drivers/startup.py
app/lookups/__init__.py
app/lookups/base.py
app/lookups/sqlite/__init__.py
app/lookups/sqlite/base.py
app/lookups/sqlite/biosets.py
app/lookups/sqlite/peptable.py
app/lookups/sqlite/protpeptable.py
app/lookups/sqlite/prottable.py
app/lookups/sqlite/psms.py
app/lookups/sqlite/quant.py
app/lookups/sqlite/searchspace.py
app/lookups/sqlite/spectra.py
app/readers/__init__.py
app/readers/fasta.py
app/readers/mzidplus.py
app/readers/openms.py
app/readers/percolator.py
app/readers/spectra.py
app/readers/tsv.py
app/readers/xml.py
app/readers/xmlformatting.py
app/writers/__init__.py
app/writers/percolator.py
app/writers/tsv.py
msstitch-3.17.dist-info/LICENSE
msstitch-3.17.dist-info/METADATA
msstitch-3.17.dist-info/WHEEL
msstitch-3.17.dist-info/entry_points.txt
msstitch-3.17.dist-info/top_level.txt
msstitch-3.17.dist-info/RECORD
