Metadata-Version: 2.2
Name: msstitch
Version: 3.17
Summary: MS proteomics post processing utilities
Home-page: https://github.com/lehtiolab/msstitch
Author: Jorrit Boekel
Author-email: jorrit.boekel@scilifelab.se
Maintainer: Jorrit Boekel
Maintainer-email: jorrit.boekel@scilifelab.se
License: MIT
Keywords: mass spectrometry,proteomics,processing
Classifier: Development Status :: 5 - Production/Stable
Classifier: Intended Audience :: Science/Research
Classifier: Natural Language :: English
Classifier: License :: OSI Approved :: MIT License
Classifier: Operating System :: OS Independent
Classifier: Programming Language :: Python
Classifier: Programming Language :: Python :: 3
Classifier: Programming Language :: Python :: 3.7
Classifier: Programming Language :: Python :: 3.8
Classifier: Programming Language :: Python :: Implementation :: CPython
Classifier: Topic :: Scientific/Engineering :: Bio-Informatics
License-File: LICENSE
Requires-Dist: numpy
Requires-Dist: lxml
Requires-Dist: biopython
Dynamic: author
Dynamic: author-email
Dynamic: classifier
Dynamic: description
Dynamic: description-content-type
Dynamic: home-page
Dynamic: keywords
Dynamic: license
Dynamic: maintainer
Dynamic: maintainer-email
Dynamic: requires-dist
Dynamic: summary
